gradio_autopilot_chatbot/__init__.py
gradio_autopilot_chatbot/agentchatbot.py
gradio_autopilot_chatbot/agentchatbot.pyi
gradio_autopilot_chatbot/templates/component/Index-BpWUvslZ.js
gradio_autopilot_chatbot/templates/component/_basePickBy-DONN9-hQ.js
gradio_autopilot_chatbot/templates/component/_baseUniq-orsuDmiP.js
gradio_autopilot_chatbot/templates/component/arc-BPrXDw74.js
gradio_autopilot_chatbot/templates/component/architectureDiagram-W76B3OCA-DSvXx8bs.js
gradio_autopilot_chatbot/templates/component/auto-render-BwaQGe8P.js
gradio_autopilot_chatbot/templates/component/blockDiagram-QIGZ2CNN-BcM6k-1B.js
gradio_autopilot_chatbot/templates/component/c4Diagram-FPNF74CW-DvTkG7jZ.js
gradio_autopilot_chatbot/templates/component/channel-7VdGX7Ow.js
gradio_autopilot_chatbot/templates/component/chunk-4BX2VUAB-DwVPPsbL.js
gradio_autopilot_chatbot/templates/component/chunk-55IACEB6-C0Zdfnlq.js
gradio_autopilot_chatbot/templates/component/chunk-FMBD7UC4-DElDzMjQ.js
gradio_autopilot_chatbot/templates/component/chunk-K7UQS3LO-CV9R-yof.js
gradio_autopilot_chatbot/templates/component/chunk-QN33PNHL-CISg-vhk.js
gradio_autopilot_chatbot/templates/component/chunk-QZHKN3VN-CAdD1GGJ.js
gradio_autopilot_chatbot/templates/component/chunk-TVAH2DTR-B5XjqY8F.js
gradio_autopilot_chatbot/templates/component/chunk-TZMSLE5B-KWyGNZlF.js
gradio_autopilot_chatbot/templates/component/classDiagram-KNZD7YFC-pSBL3Lu6.js
gradio_autopilot_chatbot/templates/component/classDiagram-v2-RKCZMP56-pSBL3Lu6.js
gradio_autopilot_chatbot/templates/component/clone-DVqAzcgp.js
gradio_autopilot_chatbot/templates/component/cose-bilkent-S5V4N54A-DB073bsr.js
gradio_autopilot_chatbot/templates/component/cytoscape.esm-ZmItrg9y.js
gradio_autopilot_chatbot/templates/component/dagre-5GWH7T2D-CeIuVuOe.js
gradio_autopilot_chatbot/templates/component/defaultLocale-D7EN2tov.js
gradio_autopilot_chatbot/templates/component/diagram-N5W7TBWH-BGgupeLJ.js
gradio_autopilot_chatbot/templates/component/diagram-QEK2KX5R-DKIWvuOe.js
gradio_autopilot_chatbot-0.0.4.dist-info/METADATA
gradio_autopilot_chatbot-0.0.4.dist-info/WHEEL
gradio_autopilot_chatbot-0.0.4.dist-info/RECORD
